_madoka.cpython-37m-darwin.so
madoka/__init__.py
madoka/madoka.py
madoka-0.7.1.dist-info/LICENSE
madoka-0.7.1.dist-info/METADATA
madoka-0.7.1.dist-info/WHEEL
madoka-0.7.1.dist-info/top_level.txt
madoka-0.7.1.dist-info/RECORD
